pipTestPackage/__init__.py
pipTestPackage/pipTestPackage.py
pipTestPackage-0.0.4.dist-info/DESCRIPTION.rst
pipTestPackage-0.0.4.dist-info/LICENSE.txt
pipTestPackage-0.0.4.dist-info/METADATA
pipTestPackage-0.0.4.dist-info/RECORD
pipTestPackage-0.0.4.dist-info/WHEEL
pipTestPackage-0.0.4.dist-info/metadata.json
pipTestPackage-0.0.4.dist-info/top_level.txt
test/__init__.py
test/pipTestPackage.py
