Metadata-Version: 2.0
Name: pipTestPackage
Version: 0.0.4
Summary: Test Packaging
Home-page: https://github.com/goodboychan/pipTestPackage
Author: Chanseok Kang
Author-email: chanseok.kang@lge.com
License: MIT
Keywords: test package development
Platform: UNKNOWN
Requires-Dist: numpy
Requires-Dist: matplotlib
